CHANGES.txt
COPYRIGHT.txt
LICENSE.txt
bootstrap.py
buildout.cfg
setup.py
src/z3c/__init__.py
src/z3c.quickentry.egg-info/PKG-INFO
src/z3c.quickentry.egg-info/SOURCES.txt
src/z3c.quickentry.egg-info/dependency_links.txt
src/z3c.quickentry.egg-info/namespace_packages.txt
src/z3c.quickentry.egg-info/not-zip-safe
src/z3c.quickentry.egg-info/requires.txt
src/z3c.quickentry.egg-info/top_level.txt
src/z3c/quickentry/README.txt
src/z3c/quickentry/__init__.py
src/z3c/quickentry/interfaces.py
src/z3c/quickentry/plugin.py
src/z3c/quickentry/processor.py
src/z3c/quickentry/tests.py